setup.py
tscproject/__init__.py
tscproject/tsc.py
tscproject.egg-info/PKG-INFO
tscproject.egg-info/SOURCES.txt
tscproject.egg-info/dependency_links.txt
tscproject.egg-info/entry_points.txt
tscproject.egg-info/top_level.txt