Metadata-Version: 1.0
Name: tscproject
Version: 0.0.1
Summary: A simple tool for init typescript skeleton project.
Home-page: https://github.com/husu/typeProject_initializer
Author: qorzj
Author-email: inull@qq.com
License: MIT
Keywords: typescript tsc tscproject
Platform: any
